whatsappening/__init__.py
whatsappening/main.py
whatsappening_cli-1.3.0.dist-info/LICENSE
whatsappening_cli-1.3.0.dist-info/METADATA
whatsappening_cli-1.3.0.dist-info/WHEEL
whatsappening_cli-1.3.0.dist-info/entry_points.txt
whatsappening_cli-1.3.0.dist-info/top_level.txt
whatsappening_cli-1.3.0.dist-info/RECORD
