Metadata-Version: 2.1
Name: whatsappening-cli
Version: 1.3.0
Summary: A WhatsApp activity tracker
Home-page: https://www.github.com/KarthikeyanRanasthala/WhatsAppening
Author: Karthikeyan Ranasthala
License: UNKNOWN
Project-URL: Source, https://www.github.com/KarthikeyanRanasthala/WhatsAppening
Keywords: whatsapp tracker tracking monitor monitoring
Platform: UNKNOWN
Classifier: Development Status :: 5 - Production/Stable
Classifier: License :: OSI Approved :: MIT License
Classifier: Programming Language :: Python :: 3.6
Classifier: Programming Language :: Python :: 3.7
Requires-Python: >= 3.6
Requires-Dist: firebase-admin
Requires-Dist: selenium
